dagster_vertexai/__init__.py
dagster_vertexai/resource.py
dagster_vertexai-0.0.1.dist-info/METADATA
dagster_vertexai-0.0.1.dist-info/WHEEL
dagster_vertexai-0.0.1.dist-info/top_level.txt
dagster_vertexai-0.0.1.dist-info/RECORD
