Metadata-Version: 2.4
Name: dagster-vertexai
Version: 0.0.1
Summary: Dagster integration for Google Cloud Vertex AI
Requires-Python: >=3.9
Requires-Dist: dagster>=1.11.9
Requires-Dist: google-cloud-aiplatform>=1.55.0
Requires-Dist: google-auth
